Metadata-Version: 2.1
Name: sillybot
Version: 0.1
Summary: SillyBot: fastest way to develop scrapping bots
Home-page: https://40uf411.github.io/SillyBot/
Author: Ali Aouf
Author-email: 40uf4l1@gmail.com
License: GPL
Platform: UNKNOWN
Classifier: Development Status :: 5 - Production/Stable
Classifier: Intended Audience :: End Users/Desktop
Classifier: Operating System :: OS Independent
Classifier: Programming Language :: Python
License-File: LICENSE
